{
  "project_info": {
    "project_number": "252736223486",
    "project_id": "mrl-todo-app",
    "storage_bucket": "mrl-todo-app.firebasestorage.app"
  },
  "client": [
    {
      "client_info": {
        "mobilesdk_app_id": "1:252736223486:android:753155b8bdd19e816c8daf",
        "android_client_info": {
          "package_name": "com.example.todo_app"
        }
      },
      "oauth_client": [],
      "api_key": [
        {
          "current_key": "AIzaSyDqqiXE9wWmNIImBrxwUO8HVmoU8mBbf4o"
        }
      ],
      "services": {
        "appinvite_service": {
          "other_platform_oauth_client": []
        }
      }
    }
  ],
  "configuration_version": "1"
}